package2cve
