Metadata-Version: 2.1
Name: package2cve
Version: 0.7
Summary: Give a hostname to get package CVE or pass a package name plus version
Home-page: https://github.com/fernandocastrovilar/package2cve
Download-URL: https://github.com/fernandocastrovilar/package2cve/archive/v_07.tar.gz
Author: Fernando Castro
Author-email: whit3bl0cker@gmail.com
License: MIT
License-File: LICENSE.txt
